Metadata-Version: 2.1
Name: gaussian_binom
Version: 0.1
Summary: Gaussian and Binomial distributions
Author: Jason Ndirangu
Author-email: bgathendu@live.com
